[
    {
        "component": "Name",
        "name": "Amplifier"
    },
    {
        "component": "House",
        "houses": [
            "Robots"
        ]
    },
    {
        "component": "Description",
        "text": "On buy:\nShield\nreflects damage"
    },
    {
        "component": "AbilityDescription",
        "abilities": [
            "Shield"
        ]
    },
    {
        "component": "Hp",
        "max": 2
    },
    {
        "component": "Attack",
        "value": 2
    },
    {
        "component": "Shader",
        "path": "shaders/system/unit.glsl",
        "layer": "Unit",
        "chain": [
            {
                "component": "Shader",
                "path": "shaders/vfx/circle.glsl",
                "parameters": {
                    "uniforms": {
                        "u_color": "#00aacc"
                    }
                }
            }
        ]
    },
    {
        "component": "StatusContainer",
        "statuses": {
            "ShieldAddReflect": {
                "trigger": {
                    "type": "Buy",
                    "effect": {
                        "type": "List",
                        "effects": [
                            {
                                "type": "SetAbilityVarInt",
                                "house": "Robots",
                                "ability": "Shield",
                                "var": "Reflection",
                                "value": {
                                    "type": "Const",
                                    "value": 1
                                }
                            },
                            {
                                "type": "ShowText",
                                "text": "++Shield Reflection",
                                "color": "#00e9c6"
                            }
                        ]
                    }
                }
            }
        }
    }
]