{
    "hp": 5,
    "speed": 1,
    "projectile_speed": 10.0,
    "size": 1,
    "attack": {
        "damage": 2,
        "radius": 0.5,
        "animation_delay": 0.5,
        "cooldown": 0.5
    },
    "on": {
        "Death": [
            {
                "type": "Spawn",
                "unit_type": "small_blob"
            },
            {
                "type": "Spawn",
                "unit_type": "small_blob"
            },
            {
                "type": "Spawn",
                "unit_type": "small_blob"
            },
            {
                "type": "Spawn",
                "unit_type": "small_blob"
            }
        ]
    },
    "move_ai": "Advance",
    "target_ai": "Closest",
    "color": "yellow"
}