    {
        "name": "Cleanser",
        "description": "On Buy:\nDispel\nadjacent allies",
        "health": 5,
        "attack": 2,
        "houses": [
            "Exorcists"
        ],
        "trigger": {
            "type": "OnBuy",
            "effect": {
                "type": "List",
                "effects": [
                    {
                        "type": "If",
                        "condition": {
                            "type": "SlotOccupied",
                            "faction": "Team",
                            "slot": {
                                "type": "Sum",
                                "a": {
                                    "type": "Var",
                                    "var": "Slot"
                                },
                                "b": {
                                    "type": "Const",
                                    "value": 1
                                }
                            }
                        },
                        "then": {
                            "type": "UseAbility",
                            "target": {
                                "type": "FindUnit",
                                "slot": {
                                    "type": "Sum",
                                    "a": {
                                        "type": "Var",
                                        "var": "Slot"
                                    },
                                    "b": {
                                        "type": "Const",
                                        "value": 1
                                    }
                                },
                                "faction": {
                                    "type": "Owner"
                                }
                            },
                            "name": "Dispel"
                        },
                        "else": {
                            "type": "Noop"
                        }
                    },
                    {
                        "type": "If",
                        "condition": {
                            "type": "SlotOccupied",
                            "faction": "Team",
                            "slot": {
                                "type": "Sum",
                                "a": {
                                    "type": "Var",
                                    "var": "Slot"
                                },
                                "b": {
                                    "type": "Const",
                                    "value": -1
                                }
                            }
                        },
                        "then": {
                            "target": {
                                "type": "FindUnit",
                                "slot": {
                                    "type": "Sum",
                                    "a": {
                                        "type": "Var",
                                        "var": "Slot"
                                    },
                                    "b": {
                                        "type": "Const",
                                        "value": -1
                                    }
                                },
                                "faction": {
                                    "type": "Owner"
                                }
                            },
                            "type": "UseAbility",
                            "name": "Dispel"
                        },
                        "else": {
                            "type": "Noop"
                        }
                    }
                ]
            }
        },
        "shader": {
            "path": "shaders/vfx/circle.glsl",
            "parameters": {
                "uniforms": {
                    "u_color": "#afafaf",
                    "u_circle_radius": 0.9,
                    "u_border": 0.2,
                    "u_circle_fbm": 0.1,
                    "u_circle_fbm_speed": 3.3,
                    "u_padding": 0.2,
                    "u_aa": 0.2
                }
            }
        }
    }