{
    "name": "demonic_archer+",
    "tier": 2,
    "health": 6,
    "base_damage": 8,
    "cooldown": 3,
    "description": "@Bonus Shot applies @Dark Steal. Other @Archers @Dark Steal on @Bonus Shot",
    "clans": [
        "Demons",
        "Archers"
    ],
    "statuses": [
        {
            "name": "DarkStealOnBonusShotTwice",
            "type": "Status",
            "stacking": {
                "type": "Independent"
            },
            "listeners": [
                {
                    "triggers": [
                        {
                            "type": "DamageDealt",
                            "damage_type": "BonusShot"
                        }
                    ],
                    "effect": {
                        "type": "AttachStatus",
                        "status": "DarkSteal"
                    }
                },
                {
                    "triggers": [
                        {
                            "type": "Init"
                        }
                    ],
                    "effect": {
                        "type": "AOE",
                        "filter": "Allies",
                        "skip_current_target": true,
                        "effect": {
                            "type": "If",
                            "condition": {
                                "type": "HasClan",
                                "who": "Target",
                                "clan": "Archers"
                            },
                            "then": {
                                "type": "AttachStatus",
                                "status": "DarkStealOnBonusShot"
                            },
                            "else": {
                                "type": "Noop"
                            }
                        }
                    }
                }
            ]
        }
    ],
    "base": "ranged+"
}