[
  [
    {
      "path": "shaders/clan_shaders/triangle.glsl",
      "parameters": {
        "u_count": 1,
        "u_offset": {
          "x": 0.02,
          "y": 0.31
        },
        "u_index_offset": {
          "x": 0.0,
          "y": 0.0
        },
        "u_outline_thickness": 0.0,
        "u_rotation": 0.5,
        "u_size": 0.5,
        "u_outline": 0,
        "u_fill": 1
      },
      "vertices": 0,
      "instances": 0
    },
    {
      "path": "shaders/clan_shaders/circle.glsl",
      "parameters": {
        "u_size": 0.28,
        "u_count": 1,
        "u_index_offset": {
          "x": 0.0,
          "y": 0.0
        },
        "u_offset": {
          "x": 0.0,
          "y": 0.0
        },
        "u_fill": 1,
        "u_outline": 0,
        "u_outline_thickness": 0.0
      },
      "vertices": 0,
      "instances": 0
    }
  ],
  [
    {
      "path": "shaders/clan_shaders/triangle.glsl",
      "parameters": {
        "u_count": 1,
        "u_offset": {
          "x": 0.02,
          "y": 0.31
        },
        "u_index_offset": {
          "x": 0.0,
          "y": 0.0
        },
        "u_outline_thickness": 0.0,
        "u_rotation": 0.5,
        "u_size": 0.69,
        "u_outline": 0,
        "u_fill": 1
      },
      "vertices": 0,
      "instances": 0
    },
    {
      "path": "shaders/clan_shaders/circle.glsl",
      "parameters": {
        "u_size": 0.42,
        "u_count": 1,
        "u_index_offset": {
          "x": 0.0,
          "y": 0.0
        },
        "u_offset": {
          "x": 0.0,
          "y": 0.0
        },
        "u_fill": 1,
        "u_outline": 0,
        "u_outline_thickness": 0.0
      },
      "vertices": 0,
      "instances": 0
    }
  ],
  [
    {
      "path": "shaders/clan_shaders/triangle.glsl",
      "parameters": {
        "u_count": 1,
        "u_offset": {
          "x": 0.02,
          "y": 0.31
        },
        "u_index_offset": {
          "x": 0.0,
          "y": 0.0
        },
        "u_outline_thickness": 0.1,
        "u_rotation": 0.5,
        "u_size": 0.79,
        "u_outline": 2,
        "u_fill": 1
      },
      "vertices": 0,
      "instances": 0
    },
    {
      "path": "shaders/clan_shaders/circle.glsl",
      "parameters": {
        "u_size": 0.54,
        "u_count": 1,
        "u_index_offset": {
          "x": 0.0,
          "y": 0.0
        },
        "u_offset": {
          "x": 0.0,
          "y": 0.0
        },
        "u_fill": 1,
        "u_outline": 2,
        "u_outline_thickness": 0.1
      },
      "vertices": 0,
      "instances": 0
    }
  ]
]