{
    "name": "Demons",
    "color": "#8e0039ff",
    "abilities": {
        "Empower": {
            "effect": {
                "type": "ChangeStatus",
                "name": "Empower",
                "charges": {
                    "type": "Var",
                    "var": "Charges"
                },
                "after": {
                    "type": "ShowCurve"
                }
            },
            "description": "Next damage\nincreased by 1",
            "default_vars": {
                "Charges": 1,
                "AttackExtra": 0
            }
        }
    },
    "statuses": {
        "Empower": {
            "trigger": {
                "type": "List",
                "triggers": [
                    {
                        "type": "ChangeVarInt",
                        "var": "AttackValue",
                        "delta": {
                            "type": "Sum",
                            "a": {
                                "type": "Var",
                                "var": "Charges"
                            },
                            "b": {
                                "type": "Mul",
                                "a": {
                                    "type": "Var",
                                    "var": "Charges"
                                },
                                "b": {
                                    "type": "AbilityVar",
                                    "house": "Demons",
                                    "ability": "Empower",
                                    "var": "AttackExtra"
                                }
                            }
                        }
                    },
                    {
                        "type": "AfterOutgoingDamage",
                        "effect": {
                            "type": "ChangeStatus",
                            "target": {
                                "type": "Owner"
                            },
                            "name": "Empower",
                            "charges": {
                                "type": "Sub",
                                "a": {
                                    "type": "Const",
                                    "value": 0
                                },
                                "b": {
                                    "type": "Var",
                                    "var": "Charges"
                                }
                            }
                        }
                    }
                ]
            },
            "shader": {
                "path": "shaders/status/default_status.glsl",
                "layer": "Unit"
            }
        }
    }
}